yta_parameters/__init__.py
yta_parameters/abstract.py
yta_parameters/constant.py
yta_parameters/context/__init__.py
yta_parameters/context/abstract.py
yta_parameters/context/time.py
yta_parameters/time/__init__.py
yta_parameters/time/constant.py
yta_parameters/time/eased.py
yta_parameters/types.py
yta_parameters-0.0.5.dist-info/licenses/LICENSE
yta_parameters-0.0.5.dist-info/METADATA
yta_parameters-0.0.5.dist-info/WHEEL
yta_parameters-0.0.5.dist-info/RECORD
